Metadata-Version: 2.1
Name: nexx-probability
Version: 0.1
Summary: Gaussian and Binomial distributions
Home-page: UNKNOWN
Author: Narayan Soni
License: UNKNOWN
Platform: UNKNOWN
